.gitignore
CHANGELOG
COPYING
MANIFEST.in
Makefile
README.md
setup.py
stdeb.cfg
./guild/__init__.py
./guild/__main__.py
./guild/actor.py
./guild/av.py
./guild/components.py
./guild/exceptions.py
./guild/network.py
./guild/promise.py
./guild/qtactor.py
./guild/service.py
./guild/stm.py
./guild/sketch/__init__.py
Sketches/REAME.md
Sketches/queue-gist.github.com_tierney_3996940.h
Sketches/01_threadtest/Makefile
Sketches/01_threadtest/threadtest.cpp
Sketches/02_actor/Makefile
Sketches/02_actor/actor.cpp
Sketches/03_queuetest/Makefile
Sketches/03_queuetest/README.md
Sketches/03_queuetest/actorqueue.cpp
Sketches/04_SDL/Makefile
Sketches/04_SDL/dependency.md
Sketches/04_SDL/image.bmp
Sketches/04_SDL/main.cpp
Sketches/05_queue_api/Makefile
Sketches/05_queue_api/SampleClass-X.h
Sketches/05_queue_api/SimpleActor.h
Sketches/05_queue_api/built-up.cpp
Sketches/05_queue_api/mkActor.py
Sketches/05_queue_api/parse.py
Sketches/05_queue_api/staged-preferred.cpp
Sketches/05_queue_api/staged.cpp
examples/99bottles.py
examples/av_record.py
examples/backplane_demo.py
examples/dining-philosophers.py
examples/dining-philosophers.py~
examples/dogs_go_woof_actors.py
examples/functional_actor.py
examples/functional_actor.py~
examples/promises_example.py
examples/pygame_example.py
examples/qt_video_player.py
examples/blog/accounts-1.py
examples/blog/accounts-2.py
examples/blog/accounts-3.py
examples/blog/accounts-race.py
examples/blog/accounts-race.py~
examples/blog/accounts-stm-1.py
examples/blog/accounts-stm-2.py
examples/blog/accounts-stm-3.py
examples/blog/accounts-stm-4.py
examples/blog/accounts-stm.py
examples/blog/log_watcher.py
examples/blog/recording_webcam.py
examples/blog/miniguild/benchmark.py
examples/blog/miniguild/door.py
examples/blog/miniguild/media.py
examples/blog/miniguild/miniguild.py
examples/blog/miniguild/network.py
examples/blog/miniguild/network.py~
examples/blog/miniguild/producer-consumer.py
examples/blog/miniguild/steps/1a-generators-main.py
guild.egg-info/PKG-INFO
guild.egg-info/SOURCES.txt
guild.egg-info/dependency_links.txt
guild.egg-info/top_level.txt
