Metadata-Version: 2.1
Name: guild
Version: 1.3.7
Summary: An Actor library supporting concurrency using pipelinable pythonic actors
Home-page: http://sparkslabs.com/michael/
Author: Michael Sparks (sparkslabs)
Author-email: sparks.m@gmail.com
License: Apache Software License
License-File: COPYING
